Metadata-Version: 2.1
Name: odoo13-addon-github-connector
Version: 13.0.4.0.0
Summary: Synchronize information from Github repositories
Home-page: UNKNOWN
Author: Odoo Community Association (OCA), GRAP, Akretion, Tecnativa
Author-email: support@odoo-community.org
License: AGPL-3
Platform: UNKNOWN
Classifier: Programming Language :: Python
Classifier: Framework :: Odoo
Classifier: Framework :: Odoo :: 13.0
Classifier: License :: OSI Approved :: GNU Affero General Public License v3
Requires-Python: >=3.5
Requires-Dist: GitPython
Requires-Dist: odoo (<13.1dev,>=13.0a)
Requires-Dist: pathspec
Requires-Dist: pygount
